padatious/__init__.py
padatious/bracket_expansion.py
padatious/entity.py
padatious/entity_edge.py
padatious/entity_manager.py
padatious/id_manager.py
padatious/intent.py
padatious/intent_container.py
padatious/intent_manager.py
padatious/match_data.py
padatious/pos_intent.py
padatious/simple_intent.py
padatious/train_data.py
padatious/trainable.py
padatious/training_manager.py
padatious/util.py
padatious-0.4.2.dist-info/METADATA
padatious-0.4.2.dist-info/RECORD
padatious-0.4.2.dist-info/WHEEL
padatious-0.4.2.dist-info/top_level.txt
padatious-0.4.2.dist-info/zip-safe
