Metadata-Version: 2.1
Name: padatious
Version: 0.4.2
Summary: A neural network intent parser
Home-page: http://github.com/MycroftAI/padatious
Author: Matthew Scholefield
Author-email: matthew331199@gmail.com
License: Apache-2.0
Keywords: intent-parser parser text text-processing
Platform: UNKNOWN
Classifier: Development Status :: 3 - Alpha
Classifier: Intended Audience :: Developers
Classifier: Topic :: Text Processing :: Linguistic
Classifier: License :: OSI Approved :: Apache Software License
Classifier: Programming Language :: Python :: 2
Classifier: Programming Language :: Python :: 2.7
Classifier: Programming Language :: Python :: 3
Classifier: Programming Language :: Python :: 3.0
Classifier: Programming Language :: Python :: 3.1
Classifier: Programming Language :: Python :: 3.2
Classifier: Programming Language :: Python :: 3.3
Classifier: Programming Language :: Python :: 3.4
Classifier: Programming Language :: Python :: 3.5
Classifier: Programming Language :: Python :: 3.6
Requires-Dist: fann2
Requires-Dist: xxhash
Requires-Dist: padaos
